wind_validation/__init__.py
wind_validation/_version.py
wind_validation/constants.py
wind_validation/metrics.py
wind_validation/stats.py
wind_validation/validation.py
wind_validation/hist/__init__.py
wind_validation/hist/metrics.py
wind_validation/hist/stats.py
wind_validation/reporting/__init__.py
wind_validation/reporting/plots.py
wind_validation/reporting/report.py
wind_validation/reporting/templates/aggregated.html
wind_validation/reporting/templates/comparison.html
wind_validation/reporting/templates/detailed.html
wind_validation/reporting/templates/single_point.html
wind_validation/reporting/templates/skeleton.html
wind_validation/reporting/templates/style.css
wind_validation/reporting/templates/static/Corp_Red_RGB.png
wind_validation/reporting/templates/static/Windsider_BIG_Logo_Color.png
wind_validation/ts/__init__.py
wind_validation/ts/metrics.py
wind_validation/ts/stats.py
wind_validation/weib/__init__.py
wind_validation/weib/metrics.py
wind_validation/weib/stats.py
wind_validation-1.0.1.dist-info/LICENSE
wind_validation-1.0.1.dist-info/METADATA
wind_validation-1.0.1.dist-info/WHEEL
wind_validation-1.0.1.dist-info/top_level.txt
wind_validation-1.0.1.dist-info/RECORD
