Metadata-Version: 2.1
Name: wind-validation
Version: 1.0.1
Summary: A tool for validating wind data
Author: DTU Wind Energy
License: BSD-3-Clause
Platform: UNKNOWN
Classifier: Programming Language :: Python :: 3
Classifier: License :: OSI Approved :: BSD License
Classifier: Operating System :: OS Independent
Requires-Python: >=3.7
License-File: LICENSE
Requires-Dist: jinja2 (>=3)
Requires-Dist: matplotlib (>=3)
Requires-Dist: numpy (>=1.21)
Requires-Dist: pandas (>=1)
Requires-Dist: plotly (>=5.1)
Requires-Dist: scipy (>=1)
Requires-Dist: windkit
Requires-Dist: xarray
Requires-Dist: xskillscore
